CHANGELOG.rst
LICENSE
MANIFEST.in
README.rst
requirements.txt
setup.py
redmin/__init__.py
redmin/apps.py
redmin/forms.py
redmin/processors.py
redmin/signals.py
redmin.egg-info/PKG-INFO
redmin.egg-info/SOURCES.txt
redmin.egg-info/dependency_links.txt
redmin.egg-info/not-zip-safe
redmin.egg-info/requires.txt
redmin.egg-info/top_level.txt
redmin/management/__init__.py
redmin/management/commands/__init__.py
redmin/management/commands/import.py
redmin/management/commands/init.py
redmin/middlewares/__init__.py
redmin/middlewares/log.py
redmin/migrations/0001_initial.py
redmin/migrations/__init__.py
redmin/models/__init__.py
redmin/models/base.py
redmin/models/choice.py
redmin/models/domain.py
redmin/models/field.py
redmin/models/filter.py
redmin/models/group.py
redmin/models/menu.py
redmin/models/permission.py
redmin/models/user.py
redmin/rest/__init__.py
redmin/rest/authentication.py
redmin/rest/exception.py
redmin/rest/metadata.py
redmin/rest/pagination.py
redmin/rest/permission.py
redmin/rest/renderer.py
redmin/rest/router.py
redmin/rest/utils.py
redmin/rest/serializer/__init__.py
redmin/rest/serializer/base.py
redmin/rest/view/__init__.py
redmin/rest/view/account.py
redmin/rest/viewset/__init__.py
redmin/rest/viewset/base.py
redmin/rest/viewset/user.py
redmin/router/__init__.py
redmin/static/redmin/ace/css/ace-ie.min.css
redmin/static/redmin/ace/css/ace-part2.min.css
redmin/static/redmin/ace/css/ace-rtl.min.css
redmin/static/redmin/ace/css/ace-skins.min.css
redmin/static/redmin/ace/css/ace.min.css
redmin/static/redmin/ace/css/bootstrap-colorpicker.min.css
redmin/static/redmin/ace/css/bootstrap-datepicker3.min.css
redmin/static/redmin/ace/css/bootstrap-datetimepicker.min.css
redmin/static/redmin/ace/css/bootstrap-duallistbox.min.css
redmin/static/redmin/ace/css/bootstrap-editable.min.css
redmin/static/redmin/ace/css/bootstrap-multiselect.min.css
redmin/static/redmin/ace/css/bootstrap-timepicker.min.css
redmin/static/redmin/ace/css/bootstrap.min.css
redmin/static/redmin/ace/css/chosen.min.css
redmin/static/redmin/ace/css/colorbox.min.css
redmin/static/redmin/ace/css/daterangepicker.min.css
redmin/static/redmin/ace/css/dropzone.min.css
